add_license_header.py
add_license_header-2.4.1.dist-info/licenses/LICENSE
add_license_header-2.4.1.dist-info/METADATA
add_license_header-2.4.1.dist-info/WHEEL
add_license_header-2.4.1.dist-info/entry_points.txt
add_license_header-2.4.1.dist-info/top_level.txt
add_license_header-2.4.1.dist-info/RECORD
