Metadata-Version: 2.4
Name: add_license_header
Version: 2.4.1
Summary: A tool for automatically adding your license as a header in your source code.
Home-page: https://github.com/arkinmodi/add-license-header
Author: Arkin Modi
Author-email: arkinmodi@gmail.com
License: MIT
Classifier: License :: OSI Approved :: MIT License
Classifier: Programming Language :: Python :: 3
Classifier: Programming Language :: Python :: 3 :: Only
Classifier: Programming Language :: Python :: Implementation :: CPython
Requires-Python: >=3.10
License-File: LICENSE
Requires-Dist: identify
Dynamic: license-file
